{
  "method": "method3",
  "model": "1dcnn_beat_level",
  "arm": "drop14",
  "mode": "v3",
  "master_manifest": "fold_composition_v3.json",
  "rollup_strategy": "max",
  "folds": {
    "0": {
      "macro_f1": 0.7026,
      "precision": 0.44,
      "recall": 0.7857,
      "specificity": 0.7627,
      "roc_auc": 0.8378,
      "pr_auc": 0.6152,
      "TP": 11,
      "TN": 45,
      "FP": 14,
      "FN": 3,
      "n_train_beats": 3716,
      "n_test_beats": 945,
      "n_test_patients": 73,
      "n_test_positive_patients": 14,
      "epochs_trained": 32,
      "mean_rollup_roc_auc": 0.8995,
      "patient_ids": [
        265715,
        314397,
        317547,
        325231,
        329034,
        450733,
        461866,
        482516,
        540736,
        596382,
        622530,
        801261,
        812404,
        821478,
        841869,
        865998,
        873255,
        891754,
        913169,
        938838,
        953976,
        967547,
        970649,
        972048,
        980284,
        982732,
        1061898,
        1063368,
        1085203,
        1097714,
        1099262,
        1106149,
        1117553,
        1124826,
        1128835,
        1152054,
        1165447,
        1187599,
        1188747,
        1192146,
        1192654,
        1202306,
        1214441,
        1238671,
        1244867,
        1275329,
        1284182,
        1290629,
        1290807,
        1305051,
        1309300,
        1310052,
        1313974,
        1326991,
        1342979,
        1370418,
        1371132,
        1385747,
        1386698,
        1414022,
        1422770,
        1426919,
        2635972,
        3015438,
        3028930,
        3058024,
        3062045,
        3065295,
        3095200,
        3099875,
        3110550,
        3113249,
        3138453
      ],
      "y_true_patient": [
        0,
        0,
        0,
        0,
        0,
        0,
        0,
        1,
        0,
        0,
        0,
        1,
        1,
        0,
        0,
        0,
        1,
        0,
        0,
        0,
        0,
        0,
        0,
        1,
        1,
        0,
        0,
        0,
        0,
        0,
        0,
        0,
        0,
        0,
        1,
        1,
        0,
        0,
        0,
        0,
        0,
        0,
        0,
        0,
        0,
        0,
        0,
        0,
        1,
        0,
        0,
        0,
        0,
        0,
        0,
        1,
        0,
        0,
        0,
        0,
        0,
        1,
        0,
        1,
        1,
        0,
        0,
        0,
        1,
        0,
        0,
        0,
        0
      ],
      "y_prob_patient": [
        0.49044737219810486,
        0.4857759177684784,
        0.8691228032112122,
        0.03586983680725098,
        0.42622485756874084,
        0.1267237514257431,
        0.5236030220985413,
        0.8252304792404175,
        0.22464092075824738,
        0.11410839110612869,
        0.5574064254760742,
        0.7062829732894897,
        0.9739888906478882,
        0.7408933639526367,
        0.3208775818347931,
        0.779735803604126,
        0.7539657354354858,
        0.8315727114677429,
        0.03740948438644409,
        0.49589478969573975,
        0.7692621946334839,
        0.827756941318512,
        0.21819232404232025,
        0.322986364364624,
        0.8490318655967712,
        0.03674192354083061,
        0.575214684009552,
        0.04453118517994881,
        0.5148100256919861,
        0.8199276924133301,
        0.879428505897522,
        0.7972359657287598,
        0.9134162068367004,
        0.2731313407421112,
        0.42641884088516235,
        0.9615222811698914,
        0.9533119797706604,
        0.18370752036571503,
        0.09549743682146072,
        0.11930229514837265,
        0.2244526743888855,
        0.8120591640472412,
        0.42682018876075745,
        0.7279099822044373,
        0.28045815229415894,
        0.41661888360977173,
        0.8281368613243103,
        0.3567858636379242,
        0.7444092631340027,
        0.147817462682724,
        0.13913965225219727,
        0.6780273914337158,
        0.03539270535111427,
        0.10652754455804825,
        0.5474202036857605,
        0.9409823417663574,
        0.39930060505867004,
        0.3519233465194702,
        0.14900647103786469,
        0.22739152610301971,
        0.2563057541847229,
        0.46519601345062256,
        0.3946865200996399,
        0.8670437335968018,
        0.9571376442909241,
        0.031536612659692764,
        0.21661671996116638,
        0.32882553339004517,
        0.899619460105896,
        0.07765897363424301,
        0.05628884211182594,
        0.02504192851483822,
        0.14621028304100037
      ],
      "y_pred_patient": [
        0,
        0,
        1,
        0,
        0,
        0,
        0,
        1,
        0,
        0,
        0,
        1,
        1,
        1,
        0,
        1,
        1,
        1,
        0,
        0,
        1,
        1,
        0,
        0,
        1,
        0,
        0,
        0,
        0,
        1,
        1,
        1,
        1,
        0,
        0,
        1,
        1,
        0,
        0,
        0,
        0,
        1,
        0,
        1,
        0,
        0,
        1,
        0,
        1,
        0,
        0,
        0,
        0,
        0,
        0,
        1,
        0,
        0,
        0,
        0,
        0,
        0,
        0,
        1,
        1,
        0,
        0,
        0,
        1,
        0,
        0,
        0,
        0
      ]
    },
    "1": {
      "macro_f1": 0.6676,
      "precision": 0.5,
      "recall": 0.55,
      "specificity": 0.7963,
      "roc_auc": 0.7519,
      "pr_auc": 0.5642,
      "TP": 11,
      "TN": 43,
      "FP": 11,
      "FN": 9,
      "n_train_beats": 3730,
      "n_test_beats": 931,
      "n_test_patients": 74,
      "n_test_positive_patients": 20,
      "epochs_trained": 27,
      "mean_rollup_roc_auc": 0.7296,
      "patient_ids": [
        188981,
        251972,
        267630,
        325966,
        329533,
        406008,
        434996,
        445953,
        505351,
        506408,
        509648,
        571723,
        581912,
        614578,
        614707,
        625190,
        812209,
        822756,
        852786,
        866721,
        878765,
        894725,
        921230,
        930107,
        958460,
        958703,
        959843,
        972330,
        994515,
        1013884,
        1058085,
        1058605,
        1084994,
        1088796,
        1093224,
        1112604,
        1121137,
        1122903,
        1138153,
        1146063,
        1165448,
        1191551,
        1199480,
        1207947,
        1220716,
        1236012,
        1238446,
        1248576,
        1254062,
        1278746,
        1285404,
        1286512,
        1297767,
        1312303,
        1336243,
        1338772,
        1344639,
        1360656,
        1366050,
        1372180,
        1404688,
        1416483,
        1418000,
        1421261,
        3009538,
        3016396,
        3016401,
        3037617,
        3043155,
        3058134,
        3067196,
        3071151,
        3072833,
        3093924
      ],
      "y_true_patient": [
        1,
        0,
        1,
        0,
        0,
        0,
        0,
        0,
        0,
        0,
        1,
        1,
        1,
        0,
        0,
        0,
        0,
        0,
        1,
        0,
        1,
        0,
        0,
        0,
        0,
        1,
        0,
        1,
        0,
        0,
        0,
        0,
        1,
        0,
        0,
        0,
        0,
        1,
        0,
        0,
        0,
        0,
        1,
        1,
        1,
        0,
        1,
        0,
        0,
        0,
        0,
        0,
        0,
        0,
        0,
        0,
        0,
        0,
        0,
        0,
        0,
        0,
        0,
        0,
        0,
        1,
        0,
        1,
        1,
        0,
        1,
        0,
        1,
        0
      ],
      "y_prob_patient": [
        0.8891538977622986,
        0.8426342606544495,
        0.5976758599281311,
        0.47015896439552307,
        0.4808761775493622,
        0.9083043932914734,
        0.5429427027702332,
        0.46036994457244873,
        0.3788694143295288,
        0.61380535364151,
        0.7376641631126404,
        0.9096108078956604,
        0.4840836524963379,
        0.3463554382324219,
        0.24189770221710205,
        0.546186625957489,
        0.5661417841911316,
        0.6152610778808594,
        0.8028279542922974,
        0.6597694158554077,
        0.40844064950942993,
        0.5147612690925598,
        0.6493087410926819,
        0.49755051732063293,
        0.4064430296421051,
        0.6821767091751099,
        0.42994898557662964,
        0.46452951431274414,
        0.7623348832130432,
        0.8327417969703674,
        0.8479247689247131,
        0.3295557200908661,
        0.856324315071106,
        0.21448230743408203,
        0.375535786151886,
        0.44851431250572205,
        0.5432197451591492,
        0.5468139052391052,
        0.4411391317844391,
        0.2536938190460205,
        0.4614088237285614,
        0.43818897008895874,
        0.7218344211578369,
        0.8002007603645325,
        0.46452951431274414,
        0.31701064109802246,
        0.6404618620872498,
        0.8416630625724792,
        0.5397429466247559,
        0.40616917610168457,
        0.26270636916160583,
        0.18540124595165253,
        0.6654183268547058,
        0.8104450702667236,
        0.5967408418655396,
        0.45950597524642944,
        0.36926499009132385,
        0.2729373276233673,
        0.6131547093391418,
        0.7698314785957336,
        0.3571562170982361,
        0.6603484153747559,
        0.7882094979286194,
        0.37386032938957214,
        0.8012643456459045,
        0.9323198199272156,
        0.4293682873249054,
        0.9252816438674927,
        0.5091266632080078,
        0.4807548224925995,
        0.6735347509384155,
        0.7959250807762146,
        0.7643746733665466,
        0.1489214301109314
      ],
      "y_pred_patient": [
        1,
        1,
        0,
        0,
        0,
        1,
        0,
        0,
        0,
        0,
        1,
        1,
        0,
        0,
        0,
        0,
        0,
        0,
        1,
        0,
        0,
        0,
        0,
        0,
        0,
        1,
        0,
        0,
        1,
        1,
        1,
        0,
        1,
        0,
        0,
        0,
        0,
        0,
        0,
        0,
        0,
        0,
        1,
        1,
        0,
        0,
        0,
        1,
        0,
        0,
        0,
        0,
        0,
        1,
        0,
        0,
        0,
        0,
        0,
        1,
        0,
        0,
        1,
        0,
        1,
        1,
        0,
        1,
        0,
        0,
        0,
        1,
        1,
        0
      ]
    },
    "2": {
      "macro_f1": 0.6506,
      "precision": 0.3889,
      "recall": 0.5385,
      "specificity": 0.8136,
      "roc_auc": 0.7784,
      "pr_auc": 0.4272,
      "TP": 7,
      "TN": 48,
      "FP": 11,
      "FN": 6,
      "n_train_beats": 3729,
      "n_test_beats": 932,
      "n_test_patients": 72,
      "n_test_positive_patients": 13,
      "epochs_trained": 29,
      "mean_rollup_roc_auc": 0.7784,
      "patient_ids": [
        286830,
        287355,
        292666,
        304141,
        413267,
        438721,
        460919,
        471727,
        482868,
        519139,
        519687,
        538053,
        548140,
        641455,
        807363,
        814286,
        822108,
        830179,
        855592,
        903442,
        907736,
        920037,
        939546,
        960432,
        962566,
        994217,
        999474,
        1023925,
        1053511,
        1054733,
        1087704,
        1092237,
        1096625,
        1102607,
        1103983,
        1118251,
        1135434,
        1147684,
        1176675,
        1183349,
        1191595,
        1207769,
        1228746,
        1231339,
        1237748,
        1248611,
        1263008,
        1272821,
        1281380,
        1294540,
        1297151,
        1297765,
        1303729,
        1327775,
        1350930,
        1357325,
        1366637,
        1381534,
        1408290,
        1422523,
        1423789,
        1424148,
        1425960,
        2187085,
        3009950,
        3037390,
        3064724,
        3074751,
        3094049,
        3114582,
        3118448,
        3128947
      ],
      "y_true_patient": [
        0,
        0,
        0,
        0,
        0,
        0,
        1,
        1,
        0,
        0,
        1,
        0,
        0,
        0,
        1,
        0,
        1,
        0,
        1,
        0,
        0,
        0,
        0,
        0,
        0,
        0,
        0,
        0,
        0,
        0,
        0,
        1,
        0,
        0,
        0,
        0,
        0,
        1,
        0,
        0,
        1,
        0,
        0,
        0,
        0,
        0,
        0,
        0,
        0,
        0,
        0,
        0,
        0,
        0,
        0,
        0,
        0,
        0,
        1,
        0,
        0,
        0,
        0,
        1,
        1,
        0,
        0,
        0,
        1,
        0,
        0,
        0
      ],
      "y_prob_patient": [
        0.2500925064086914,
        0.2511189579963684,
        0.451516717672348,
        0.46841561794281006,
        0.5649855136871338,
        0.22950273752212524,
        0.5013495087623596,
        0.8044691681861877,
        0.7755845189094543,
        0.8965723514556885,
        0.828406810760498,
        0.9309102296829224,
        0.6083778738975525,
        0.24717076122760773,
        0.7982443571090698,
        0.5937028527259827,
        0.679918646812439,
        0.8605433702468872,
        0.5975233912467957,
        0.391809344291687,
        0.31052759289741516,
        0.42732861638069153,
        0.567804217338562,
        0.4852331578731537,
        0.5817875266075134,
        0.5643768906593323,
        0.16144704818725586,
        0.20509907603263855,
        0.39991429448127747,
        0.7191809415817261,
        0.5487703680992126,
        0.7596257328987122,
        0.3258962035179138,
        0.16066646575927734,
        0.7517161965370178,
        0.09485939145088196,
        0.389740526676178,
        0.36893656849861145,
        0.5411867499351501,
        0.2824675142765045,
        0.46386653184890747,
        0.08606003224849701,
        0.41311293840408325,
        0.6608118414878845,
        0.6780403256416321,
        0.4933673143386841,
        0.2597898542881012,
        0.2464309185743332,
        0.9246304631233215,
        0.22507856786251068,
        0.1478254497051239,
        0.25410017371177673,
        0.5254423022270203,
        0.22727954387664795,
        0.27725347876548767,
        0.1356663554906845,
        0.8431928157806396,
        0.36875954270362854,
        0.8920817971229553,
        0.6541125178337097,
        0.6273780465126038,
        0.8131517767906189,
        0.3576940894126892,
        0.495611310005188,
        0.9025097489356995,
        0.916569709777832,
        0.08055373281240463,
        0.3188658356666565,
        0.9377860426902771,
        0.7075356841087341,
        0.3663632869720459,
        0.20892180502414703
      ],
      "y_pred_patient": [
        0,
        0,
        0,
        0,
        0,
        0,
        0,
        1,
        1,
        1,
        1,
        1,
        0,
        0,
        1,
        0,
        0,
        1,
        0,
        0,
        0,
        0,
        0,
        0,
        0,
        0,
        0,
        0,
        0,
        1,
        0,
        1,
        0,
        0,
        1,
        0,
        0,
        0,
        0,
        0,
        0,
        0,
        0,
        0,
        0,
        0,
        0,
        0,
        1,
        0,
        0,
        0,
        0,
        0,
        0,
        0,
        1,
        0,
        1,
        0,
        0,
        1,
        0,
        0,
        1,
        1,
        0,
        0,
        1,
        1,
        0,
        0
      ]
    },
    "3": {
      "macro_f1": 0.5969,
      "precision": 0.3333,
      "recall": 0.9286,
      "specificity": 0.5517,
      "roc_auc": 0.8768,
      "pr_auc": 0.7213,
      "TP": 13,
      "TN": 32,
      "FP": 26,
      "FN": 1,
      "n_train_beats": 3722,
      "n_test_beats": 939,
      "n_test_patients": 72,
      "n_test_positive_patients": 14,
      "epochs_trained": 33,
      "mean_rollup_roc_auc": 0.8448,
      "patient_ids": [
        267628,
        292220,
        405298,
        428031,
        466796,
        532816,
        548865,
        577838,
        592768,
        597251,
        613119,
        643139,
        816929,
        819710,
        841212,
        849168,
        898726,
        918062,
        952177,
        952641,
        969321,
        972781,
        991528,
        998036,
        1009874,
        1041375,
        1074787,
        1081032,
        1081338,
        1088175,
        1088261,
        1145203,
        1148718,
        1169405,
        1172602,
        1180702,
        1184742,
        1197538,
        1199517,
        1221590,
        1235674,
        1252288,
        1254171,
        1259391,
        1270798,
        1272319,
        1277374,
        1307673,
        1316784,
        1327784,
        1332388,
        1338780,
        1371554,
        1372181,
        1382112,
        1403173,
        1407660,
        1417008,
        3003692,
        3006598,
        3007664,
        3015440,
        3015449,
        3044775,
        3067191,
        3072836,
        3075260,
        3094047,
        3101011,
        3128957,
        3136075,
        3139196
      ],
      "y_true_patient": [
        0,
        0,
        0,
        1,
        0,
        0,
        0,
        0,
        0,
        0,
        0,
        0,
        1,
        1,
        1,
        0,
        1,
        0,
        0,
        1,
        0,
        0,
        1,
        0,
        0,
        0,
        0,
        0,
        0,
        0,
        0,
        0,
        0,
        0,
        0,
        0,
        0,
        1,
        1,
        0,
        0,
        0,
        0,
        0,
        0,
        0,
        0,
        0,
        0,
        0,
        0,
        0,
        1,
        0,
        0,
        0,
        0,
        0,
        1,
        0,
        0,
        0,
        1,
        1,
        0,
        1,
        0,
        0,
        0,
        0,
        0,
        0
      ],
      "y_prob_patient": [
        0.05803277716040611,
        0.2987363636493683,
        0.6928814649581909,
        0.9569008350372314,
        0.522457480430603,
        0.9059545397758484,
        0.21572774648666382,
        0.8243588209152222,
        0.8679589629173279,
        0.7256331443786621,
        0.5078346729278564,
        0.8033850789070129,
        0.9411606192588806,
        0.9362245798110962,
        0.8430590033531189,
        0.7236340641975403,
        0.920123815536499,
        0.4141666293144226,
        0.6953998804092407,
        0.835549533367157,
        0.5287789106369019,
        0.054168328642845154,
        0.9582986235618591,
        0.5246316194534302,
        0.34950903058052063,
        0.7921053767204285,
        0.06056331843137741,
        0.60569167137146,
        0.8913772702217102,
        0.3259223401546478,
        0.24726994335651398,
        0.7850969433784485,
        0.5965840816497803,
        0.5700889229774475,
        0.22048570215702057,
        0.10017264634370804,
        0.30716660618782043,
        0.9319029450416565,
        0.7695429921150208,
        0.8566191792488098,
        0.7860896587371826,
        0.8259997963905334,
        0.22445334494113922,
        0.7962539196014404,
        0.09160470217466354,
        0.28402939438819885,
        0.6916683316230774,
        0.9027550220489502,
        0.6865977644920349,
        0.6302912831306458,
        0.9525101184844971,
        0.7176066040992737,
        0.292081743478775,
        0.1317361295223236,
        0.8972911238670349,
        0.7430519461631775,
        0.5499124526977539,
        0.42957550287246704,
        0.9685158133506775,
        0.2625194489955902,
        0.8495590686798096,
        0.15537334978580475,
        0.8393358588218689,
        0.953370213508606,
        0.9472981095314026,
        0.9281066060066223,
        0.26523470878601074,
        0.2606160342693329,
        0.8899072408676147,
        0.8226264119148254,
        0.39702439308166504,
        0.022367412224411964
      ],
      "y_pred_patient": [
        0,
        0,
        1,
        1,
        0,
        1,
        0,
        1,
        1,
        1,
        0,
        1,
        1,
        1,
        1,
        1,
        1,
        0,
        1,
        1,
        0,
        0,
        1,
        0,
        0,
        1,
        0,
        0,
        1,
        0,
        0,
        1,
        0,
        0,
        0,
        0,
        0,
        1,
        1,
        1,
        1,
        1,
        0,
        1,
        0,
        0,
        1,
        1,
        1,
        0,
        1,
        1,
        0,
        0,
        1,
        1,
        0,
        0,
        1,
        0,
        1,
        0,
        1,
        1,
        1,
        1,
        0,
        0,
        1,
        1,
        0,
        0
      ]
    },
    "4": {
      "macro_f1": 0.6806,
      "precision": 0.4194,
      "recall": 0.8667,
      "specificity": 0.6842,
      "roc_auc": 0.8,
      "pr_auc": 0.5811,
      "TP": 13,
      "TN": 39,
      "FP": 18,
      "FN": 2,
      "n_train_beats": 3747,
      "n_test_beats": 914,
      "n_test_patients": 72,
      "n_test_positive_patients": 15,
      "epochs_trained": 32,
      "mean_rollup_roc_auc": 0.814,
      "patient_ids": [
        316872,
        319150,
        319221,
        395553,
        419510,
        419960,
        478457,
        487609,
        489539,
        516092,
        558967,
        580720,
        624511,
        806949,
        829768,
        844915,
        887465,
        903802,
        935156,
        945345,
        964469,
        965217,
        968556,
        985814,
        994065,
        1036640,
        1073253,
        1080968,
        1098314,
        1124825,
        1134284,
        1141322,
        1142915,
        1157038,
        1160261,
        1177018,
        1190805,
        1192135,
        1199593,
        1223519,
        1224102,
        1230482,
        1242678,
        1254267,
        1274776,
        1280588,
        1298469,
        1307716,
        1318568,
        1337461,
        1346727,
        1358245,
        1370819,
        1383335,
        1390489,
        1414967,
        1419825,
        1421316,
        3004284,
        3030937,
        3035210,
        3045053,
        3045059,
        3045751,
        3073346,
        3080118,
        3080186,
        3092472,
        3095195,
        3096254,
        3128412,
        3133602
      ],
      "y_true_patient": [
        0,
        1,
        0,
        0,
        0,
        1,
        0,
        0,
        0,
        0,
        0,
        0,
        0,
        0,
        0,
        0,
        0,
        0,
        0,
        1,
        0,
        1,
        0,
        0,
        0,
        0,
        0,
        0,
        1,
        0,
        0,
        1,
        0,
        1,
        0,
        0,
        0,
        0,
        0,
        0,
        1,
        1,
        0,
        1,
        0,
        0,
        0,
        0,
        0,
        0,
        0,
        1,
        0,
        0,
        1,
        0,
        0,
        0,
        1,
        0,
        0,
        0,
        0,
        0,
        0,
        1,
        1,
        0,
        0,
        0,
        0,
        0
      ],
      "y_prob_patient": [
        0.4315328299999237,
        0.7843222618103027,
        0.10319038480520248,
        0.7846843004226685,
        0.5143640637397766,
        0.8935802578926086,
        0.4197522699832916,
        0.9381721615791321,
        0.2749060094356537,
        0.10124547779560089,
        0.23932714760303497,
        0.7195917963981628,
        0.8387534618377686,
        0.5551636815071106,
        0.27138733863830566,
        0.640011727809906,
        0.23469099402427673,
        0.8760677576065063,
        0.39008548855781555,
        0.9466111063957214,
        0.06154512241482735,
        0.9732699394226074,
        0.7822042107582092,
        0.3117712736129761,
        0.8844382762908936,
        0.18569158017635345,
        0.06149575859308243,
        0.8981017470359802,
        0.9578984379768372,
        0.39798876643180847,
        0.8385897874832153,
        0.8945117592811584,
        0.192299485206604,
        0.8527662754058838,
        0.21373145282268524,
        0.5547334551811218,
        0.8188246488571167,
        0.39347028732299805,
        0.9401355981826782,
        0.9234933257102966,
        0.9290799498558044,
        0.020494090393185616,
        0.17144601047039032,
        0.7498418688774109,
        0.2885158658027649,
        0.1561286598443985,
        0.10274156183004379,
        0.7956245541572571,
        0.6128178834915161,
        0.43501728773117065,
        0.8828737139701843,
        0.5817171335220337,
        0.7597298622131348,
        0.31324705481529236,
        0.8777499794960022,
        0.6143167018890381,
        0.10920552909374237,
        0.5149803757667542,
        0.8928184509277344,
        0.6587677597999573,
        0.031274065375328064,
        0.24408157169818878,
        0.49101871252059937,
        0.9407134652137756,
        0.6625071167945862,
        0.922741711139679,
        0.7171306014060974,
        0.8123542666435242,
        0.21096813678741455,
        0.8928762674331665,
        0.3745609521865845,
        0.5953977108001709
      ],
      "y_pred_patient": [
        0,
        1,
        0,
        1,
        0,
        1,
        0,
        1,
        0,
        0,
        0,
        1,
        1,
        0,
        0,
        0,
        0,
        1,
        0,
        1,
        0,
        1,
        1,
        0,
        1,
        0,
        0,
        1,
        1,
        0,
        1,
        1,
        0,
        1,
        0,
        0,
        1,
        0,
        1,
        1,
        1,
        0,
        0,
        1,
        0,
        0,
        0,
        1,
        0,
        0,
        1,
        0,
        1,
        0,
        1,
        0,
        0,
        0,
        1,
        0,
        0,
        0,
        0,
        1,
        0,
        1,
        1,
        1,
        0,
        1,
        0,
        0
      ]
    }
  },
  "summary": {
    "macro_f1_mean": 0.6597,
    "macro_f1_std": 0.0357,
    "precision_mean": 0.4163,
    "precision_std": 0.0552,
    "recall_mean": 0.7339,
    "recall_std": 0.1614,
    "specificity_mean": 0.7217,
    "specificity_std": 0.0959,
    "roc_auc_mean": 0.809,
    "roc_auc_std": 0.0441,
    "pr_auc_mean": 0.5818,
    "pr_auc_std": 0.0946
  },
  "config": {
    "conv3_ch": 128,
    "dropout": 0.4,
    "learning_rate": 0.0001,
    "batch_size": 64,
    "max_epochs": 100,
    "early_stopping_patience": 25,
    "pos_weight": 3.6797,
    "threshold": 0.68,
    "random_seed": 42,
    "loss": "BCEWithLogitsLoss",
    "evaluation_level": "patient"
  }
}